{ "nombre" : "Grupo Popular", "acronimo" : "GP", "activo" : true }
{ "nombre" : "Grupo Vasco - EAJ PNV", "acronimo" : "GV (EAJ-PNV)", "activo" : true }
{ "nombre" : "Grupo Socialista", "acronimo" : "GS", "activo" : true }
{ "nombre" : "Grupo Mixto", "acronimo" : "GMx", "activo" : true }
{ "nombre" : "Grupo Confederal de Unidos Podemos-En Comú Podem-En Mare", "acronimo" : "GCUP-EC-EM", "activo" : true }
{ "nombre" : "Grupo Ciudadanos", "acronimo" : "GCs", "activo" : true }
{ "nombre" : "Grupo Esquerra Republicana", "acronimo" : "GER", "activo" : true }
